.DS_Store
ActflowToolbox/__init__.py
ActflowToolbox/actflowcomp/__init__.py
ActflowToolbox/actflowcomp/actflowcalc.py
ActflowToolbox/actflowcomp/actflowtest.py
ActflowToolbox/actflowcomp/noiseceilingcalc.py
ActflowToolbox/connectivity_estimation/__init__.py
ActflowToolbox/connectivity_estimation/calcactivity_parcelwise_noncircular.py
ActflowToolbox/connectivity_estimation/calcconn_parcelwise_noncircular.py
ActflowToolbox/connectivity_estimation/combinedFC.py
ActflowToolbox/connectivity_estimation/corrcoefconn.py
ActflowToolbox/connectivity_estimation/graphicalLassoCV.py
ActflowToolbox/connectivity_estimation/multregconn.py
ActflowToolbox/connectivity_estimation/partial_corrconn.py
ActflowToolbox/connectivity_estimation/pc_multregconn.py
ActflowToolbox/dependencies/__init__.py
ActflowToolbox/examples/__init__.py
ActflowToolbox/model_compare/__init__.py
ActflowToolbox/model_compare/model_compare.py
ActflowToolbox/model_compare/model_compare_predicted_to_actual.py
ActflowToolbox/network_definitions/__init__.py
ActflowToolbox/network_definitions/calc_removal_coords.py
ActflowToolbox/network_definitions/dilateParcels.py
ActflowToolbox/network_definitions/prep_noncirc.py
ActflowToolbox/simulations/__init__.py
ActflowToolbox/tools/__init__.py
ActflowToolbox/tools/addNetColors.py
ActflowToolbox/tools/addNetColors_Seaborn.py
ActflowToolbox/tools/map_to_surface.py
ActflowToolbox/tools/max_r.py
ActflowToolbox/tools/max_t.py
ActflowToolbox/tools/regression.py
ActflowToolbox-0.3.0.dist-info/METADATA
ActflowToolbox-0.3.0.dist-info/WHEEL
ActflowToolbox-0.3.0.dist-info/top_level.txt
ActflowToolbox-0.3.0.dist-info/RECORD
