Metadata-Version: 2.1
Name: ActflowToolbox
Version: 0.3.0
Summary: The Brain Activity Flow (Actflow) Toolbox. Tools to quantify the relationship between connectivity and task activity through network simulations and machine learning prediction. Helps determine how connections contribute to specific brain functions.
Home-page: https://github.com/ColeLab/ActflowToolbox
Author: Michael Cole
Author-email: michael.cole@rutgers.edu
License: The Brain Activity Flow Toolbox (Actflow Toolbox),
Classifier: Programming Language :: Python :: 3
Classifier: License :: Other/Proprietary License
Classifier: Operating System :: OS Independent
Requires-Python: >=3.0
Requires-Dist: gglasso
Requires-Dist: wbplot
Requires-Dist: seaborn
Requires-Dist: matplotlib
Requires-Dist: numpy (<=1.24)
Requires-Dist: h5py
Requires-Dist: statsmodels
